biblematetc/README.md
biblematetc/__init__.py
biblematetc/bible_study_mcp.py
biblematetc/biblematemcp.py
biblematetc/config.py
biblematetc/main.py
biblematetc/package_name.txt
biblematetc/requirements.txt
biblematetc/version.txt
biblematetc/core/systems.py
biblematetc/etextedit/README.md
biblematetc/etextedit/plugins/Extract Bible References.py
biblematetc/etextedit/plugins/Insert Bible Text.py
biblematetc/etextedit/plugins/Translate into Traditional Chinese.py
biblematetc/uba/add_vector.py
biblematetc/uba/api.py
biblematetc/uba/bible.py
biblematetc/uba/dialogs.py
biblematetc/uba/search.py
biblematetc/ui/info.py
biblematetc/ui/prompts.py
biblematetc/ui/selection_dialog.py
biblematetc/ui/text_area.py
biblematetc-0.2.50.dist-info/METADATA
biblematetc-0.2.50.dist-info/WHEEL
biblematetc-0.2.50.dist-info/entry_points.txt
biblematetc-0.2.50.dist-info/top_level.txt
biblematetc-0.2.50.dist-info/RECORD
