Metadata-Version: 2.1
Name: biblematetc
Version: 0.2.50
Summary: BibleMate AI - Automate Your Bible Study
Home-page: https://biblemate.ai
Author: Eliran Wong
Author-email: support@marvel.bible
License: GNU General Public License (GPL)
Project-URL: Source, https://github.com/eliranwong/biblematetc
Project-URL: Tracker, https://github.com/eliranwong/biblematetc/issues
Project-URL: Documentation, https://github.com/eliranwong/biblematetc/wiki
Project-URL: Funding, https://www.paypal.me/MarvelBible
Keywords: mcp agent biblemate ai anthropic azure chatgpt cohere deepseek genai github googleai groq llamacpp mistral ollama openai vertexai xai
Classifier: Development Status :: 5 - Production/Stable
Classifier: Intended Audience :: End Users/Desktop
Classifier: Topic :: Utilities
Classifier: Topic :: Scientific/Engineering :: Artificial Intelligence
Classifier: Topic :: Software Development :: Build Tools
Classifier: License :: OSI Approved :: GNU General Public License v3 or later (GPLv3+)
Classifier: Programming Language :: Python :: 3.10
Classifier: Programming Language :: Python :: 3.11
Classifier: Programming Language :: Python :: 3.12
Requires-Python: >=3.10, <3.13
Requires-Dist: agentmake >=1.1.80
Requires-Dist: agentmakemcp >=0.0.8
Requires-Dist: alive-progress
Requires-Dist: click
Requires-Dist: fastmcp[cli]
Requires-Dist: gdown
Requires-Dist: rich
Provides-Extra: genai
Requires-Dist: google-genai >=1.46.0 ; extra == 'genai'
